{
  "type": "Feature",
  "properties": {
    "gn:admin1_code":"9.0",
    "gn:asciiname":"Harrington Hundreds",
    "gn:country_code":"BM",
    "gn:dem":44,
    "gn:feature_class":"P",
    "gn:feature_code":"PPL",
    "gn:name":"Harrington Hundreds",
    "gn:population":0,
    "gn:timezone":"Atlantic/Bermuda",
    "iso:country":"BM",
    "wof:name":"Harrington Hundreds",
    "wof:placetype":"locality"
},
  "geometry": {"coordinates":[-64.72889000000001,32.31861],"type":"Point"}
}