{
  "type": "Feature",
  "properties": {
    "gn:admin1_code":"7.0",
    "gn:asciiname":"Melrose",
    "gn:country_code":"BM",
    "gn:dem":27,
    "gn:feature_class":"P",
    "gn:feature_code":"PPL",
    "gn:name":"Melrose",
    "gn:population":0,
    "gn:timezone":"Atlantic/Bermuda",
    "iso:country":"BM",
    "name:cat_x_preferred":[
        "Melrose"
    ],
    "name:ceb_x_preferred":[
        "Melrose"
    ],
    "name:cym_x_preferred":[
        "Melrose"
    ],
    "name:deu_x_preferred":[
        "Melrose"
    ],
    "name:fin_x_preferred":[
        "Melrose"
    ],
    "name:fra_x_preferred":[
        "Melrose"
    ],
    "name:hun_x_preferred":[
        "Melrose"
    ],
    "name:ita_x_preferred":[
        "Melrose"
    ],
    "name:jpn_x_preferred":[
        "\u30e1\u30eb\u30ed\u30fc\u30ba"
    ],
    "name:nld_x_preferred":[
        "Melrose"
    ],
    "name:pol_x_preferred":[
        "Melrose"
    ],
    "name:por_x_preferred":[
        "Melrose"
    ],
    "name:rus_x_preferred":[
        "\u041c\u0435\u043b\u0440\u043e\u0437"
    ],
    "name:sco_x_preferred":[
        "Melrose"
    ],
    "name:spa_x_preferred":[
        "Melrose"
    ],
    "name:srp_x_preferred":[
        "\u041c\u0435\u043b\u0440\u043e\u0443\u0437"
    ],
    "name:swe_x_preferred":[
        "Melrose"
    ],
    "name:ukr_x_preferred":[
        "\u041c\u0435\u043b\u0440\u043e\u0443\u0437"
    ],
    "name:vol_x_preferred":[
        "Melrose"
    ],
    "wof:name":"Melrose",
    "wof:placetype":"locality"
},
  "geometry": {"coordinates":[-64.67739,32.36845],"type":"Point"}
}