{
  "type": "Feature",
  "properties": {
    "gn:admin1_code":"7.0",
    "gn:asciiname":"Melrose",
    "gn:country_code":"BM",
    "gn:dem":27,
    "gn:feature_class":"P",
    "gn:feature_code":"PPL",
    "gn:name":"Melrose",
    "gn:population":0,
    "gn:timezone":"Atlantic/Bermuda",
    "iso:country":"BM",
    "wof:name":"Melrose",
    "wof:placetype":"locality"
},
  "geometry": {"coordinates":[-64.67739,32.36845],"type":"Point"}
}