{
  "type": "Feature",
  "properties": {
    "gn:admin1_code":"4.0",
    "gn:asciiname":"Mount Pleasant",
    "gn:country_code":"BM",
    "gn:dem":37,
    "gn:feature_class":"P",
    "gn:feature_code":"PPL",
    "gn:name":"Mount Pleasant",
    "gn:population":0,
    "gn:timezone":"Atlantic/Bermuda",
    "iso:country":"BM",
    "name:bar_x_preferred":[
        "Mount Pleasant"
    ],
    "name:cat_x_preferred":[
        "Mount Pleasant"
    ],
    "name:ceb_x_preferred":[
        "Mount Pleasant"
    ],
    "name:ces_x_preferred":[
        "Mount Pleasant"
    ],
    "name:deu_x_preferred":[
        "Mount Pleasant"
    ],
    "name:fra_x_preferred":[
        "Mount Pleasant"
    ],
    "name:ita_x_preferred":[
        "Mount Pleasant"
    ],
    "name:jpn_x_preferred":[
        "\u30de\u30a6\u30f3\u30c8\u30fb\u30d7\u30ec\u30b6\u30f3\u30c8"
    ],
    "name:kor_x_preferred":[
        "\ub9c8\uc6b4\ud2b8\ud50c\ub808\uc804\ud2b8"
    ],
    "name:mlg_x_preferred":[
        "Mount Pleasant"
    ],
    "name:nld_x_preferred":[
        "Mount Pleasant"
    ],
    "name:nor_x_preferred":[
        "Mount Pleasant"
    ],
    "name:pol_x_preferred":[
        "Mount Pleasant"
    ],
    "name:por_x_preferred":[
        "Mount Pleasant"
    ],
    "name:rus_x_preferred":[
        "\u041c\u0430\u0443\u043d\u0442-\u041f\u043b\u0435\u0437\u0430\u043d\u0442"
    ],
    "name:spa_x_preferred":[
        "Mount Pleasant"
    ],
    "name:srp_x_preferred":[
        "\u041c\u0430\u0443\u043d\u0442 \u041f\u043b\u0435\u0437\u0430\u043d\u0442"
    ],
    "name:swe_x_preferred":[
        "Mount Pleasant"
    ],
    "name:ukr_x_preferred":[
        "\u041c\u0430\u0443\u043d\u0442-\u041f\u043b\u0435\u0437\u0430\u043d\u0442"
    ],
    "name:vol_x_preferred":[
        "Mount Pleasant"
    ],
    "wof:name":"Mount Pleasant",
    "wof:placetype":"locality"
},
  "geometry": {"coordinates":[-64.78361,32.27417],"type":"Point"}
}