{
  "type": "Feature",
  "properties": {
    "gn:admin1_code":"4.0",
    "gn:asciiname":"Mount Pleasant",
    "gn:country_code":"BM",
    "gn:dem":37,
    "gn:feature_class":"P",
    "gn:feature_code":"PPL",
    "gn:name":"Mount Pleasant",
    "gn:population":0,
    "gn:timezone":"Atlantic/Bermuda",
    "iso:country":"BM",
    "wof:name":"Mount Pleasant",
    "wof:placetype":"locality"
},
  "geometry": {"coordinates":[-64.78361,32.27417],"type":"Point"}
}